{
  "gray04": "#4c4b4e",
  "gray05": "#5c595f",
  "gray06": "#6b676f",
  "gray07": "#78737d",
  "gray08": "#8c8792",
  "gray09": "#9c96a2",
  "gray0a": "#a8a1af",
  "gray0b": "#b8b1be",
  "gray0c": "#c9c4cf",
  "gray0d": "#dbd7e0",
  "gray0e": "#e8e5eb",
  "gray0f": "#f7f6f9",
  "white": "#fdfdfe",
  "green": "#9bae7e",
  "greenLight": "#d1dac3",
  "greenLighter": "#e7ebe0",
  "greenContrast": "#667e44",
  "teal": "#5f9b8d",
  "tealLight": "#adccc5",
  "tealLighter": "#d6e6e2",
  "tealContrast": "#468173",
  "blue": "#80a4be",
  "blueLight": "#bfd1de",
  "blueLighter": "#dfe8ef",
  "blueContrast": "#527b98",
  "purple": "#ac9bc5",
  "purpleLight": "#d7cfe3",
  "purpleLighter": "#ebe7f1",
  "purpleContrast": "#806f9b",
  "red": "#d67e76",
  "redLight": "#e5ada8",
  "redLighter": "#f3dcda",
  "redContrast": "#c06159",
  "orange": "#de9e59",
  "orangeLight": "#eeceac",
  "orangeLighter": "#f7e7d5",
  "orangeContrast": "#bf8240",
  "yellow": "#e6c565",
  "yellowLight": "#e9d9a8",
  "yellowLighter": "#f7f0de",
  "yellowContrast": "#b39119",
  "brightPink": "#e87da4",
  "brightPinkLight": "#f0a8c2",
  "brightPinkLighter": "#fae1ea",
  "brightYellow": "#f5da70",
  "brightYellowLight": "#f8e7a0",
  "brightYellowLighter": "#fdf6de"
}
